README.rst
dragons.py
setup.py
dragons.egg-info/PKG-INFO
dragons.egg-info/SOURCES.txt
dragons.egg-info/dependency_links.txt
dragons.egg-info/top_level.txt