Metadata-Version: 1.1
Name: dragons
Version: 1.0.0
Summary: Dragons! A bit of fun.
Home-page: https://github.com/alexwlchan/dragons
Author: Alex Chan
Author-email: alex@alexwlchan.net
License: MIT
Platform: UNKNOWN
Classifier: Development Status :: 5 - Production/Stable
Classifier: License :: OSI Approved :: MIT License
Classifier: Natural Language :: English
Classifier: Programming Language :: Python :: 2.7
Classifier: Programming Language :: Python :: 3
Classifier: Programming Language :: Python :: 3.4
Classifier: Programming Language :: Python :: 3.5
Classifier: Programming Language :: Python :: 3.6
